{
    "code": 1,
    "content":[{
        "name": "天涯",
        "qq": 1664403457,
        "type": 1,
        "msg": "今天份奇奇怪怪4.19"
    },
    {
        "name": "天涯",
        "qq": 1664403457,
        "type": 3,
        "msg": [
            "",
            "https://qqq.gtimg.cn/music/photo_new/T053XD0000022gIlT2BM38m.png",
            "每日一捉！好像还是个围成年？<br> https://v.163.com/1402946421778285952/720.m3u8"
        ]
    },
    {
        "name": "天涯",
        "qq": 1664403457,
        "type": 3,
        "msg": [
            "",
            "https://qqq.gtimg.cn/music/photo_new/T053XD000001nWmDJ0R6qIT.png",
            "抢钱就算了，你他妈还灭口，真是个畜生<br> https://v.163.com/1402961617825563136/720.m3u8"
        ]
    },
    {
        "name": "天涯",
        "qq": 1664403457,
        "type": 3,
        "msg": [
            "",
            "https://qqq.gtimg.cn/music/photo_new/T053XD000002o3ZqD0jqPSV.jpg",
            "腿控鉴赏！<br> http://yyds-1259597897.cos.ap-chengdu.myqcloud.com/index.html#419951"
        ]
    },
    {
        "name": "天涯",
        "qq": 1664403457,
        "type": 3,
        "msg": [
            "",
            "https://qqq.gtimg.cn/music/photo_new/T053XD000001FdcLG1knU7f.png",
            "卧槽@断了？ <br> https://v.163.com/1403008058820395776/720.m3u8"
        ]
    },
    {
        "name": "天涯",
        "qq": 1664403457,
        "type": 3,
        "msg": [
            "",
            "https://qqq.gtimg.cn/music/photo_new/T053XD000000xgWPg1p9oUZ.png",
            "王馨瑶 地下车库 <br> 好久没看到这个烧鸡了 <br> https://v.163.com/1403014024790017408/720.m3u8"
        ]
    }
] }
