{
    "code": 1,
    "content": [
        {
            "name": "天涯",
            "qq": 36937883,
            "type": 3,
            "msg": [
                "花钱找罪受不玩了 ",
                "",
                ""
            ]
        },
        {
            "name": "天涯",
            "qq": 36937883,
            "type": 3,
            "msg": [
                "",
                "https://qqq.gtimg.cn/music/photo_new/T053XD000003d9y5D0y4Grp.jpg",
                ""
            ]
        },
        {
            "name": "天涯",
            "qq": 36937883,
            "type": 3,
            "msg": [
                "",
                "https://qqq.gtimg.cn/music/photo_new/T053XD0000029B8YB44MRhu.jpg",
                ""
            ]
        },
        {
            "name": "天涯",
            "qq": 36937883,
            "type": 3,
            "msg": [
                "",
                "https://qqq.gtimg.cn/music/photo_new/T053XD000002ViIzN0vLJt1.jpg",
                ""
            ]
        },
        {
            "name": "天涯",
            "qq": 36937883,
            "type": 3,
            "msg": [
                "",
                "https://qqq.gtimg.cn/music/photo_new/T053XD000000S9h3u0D6RZS.jpg",
                ""
            ]
        },
        {
            "name": "天涯",
            "qq": 36937883,
            "type": 3,
            "msg": [
                "",
                "https://qqq.gtimg.cn/music/photo_new/T053XD000001XyhD71V2qvr.jpg",
                ""
            ]
        },
        {
            "name": "天涯",
            "qq": 36937883,
            "type": 3,
            "msg": [
                "",
                "https://qqq.gtimg.cn/music/photo_new/T053XD000001je88I0CWBYJ.jpg",
                ""
            ]
        },
        {
            "name": "天涯",
            "qq": 36937883,
            "type": 3,
            "msg": [
                "",
                "https://qqq.gtimg.cn/music/photo_new/T053XD000003o1oNl28expC.jpg",
                ""
            ]
        },
        {
            "name": "天涯",
            "qq": 36937883,
            "type": 3,
            "msg": [
                "",
                "https://qqq.gtimg.cn/music/photo_new/T053XD000001MG9fE4ZmBfJ.jpg",
                ""
            ]
        }
    ]
}