{
    "code": 1,
    "content": [
        {
            "name": "天涯",
            "qq": 36937883,
            "type": 3,
            "msg": [
                "投稿 网友约P翻车现场",
                "",
                ""
            ]
        },
        {
            "name": "天涯",
            "qq": 36937883,
            "type": 3,
            "msg": [
                "",
                "https://qqq.gtimg.cn/music/photo_new/T053XD000000l0HM23tgGk7.jpg",
                ""
            ]
        },
        {
            "name": "天涯",
            "qq": 36937883,
            "type": 3,
            "msg": [
                "",
                "https://qqq.gtimg.cn/music/photo_new/T053XD000001omJ1A2AME5U.jpg",
                ""
            ]
        },
        {
            "name": "天涯",
            "qq": 36937883,
            "type": 3,
            "msg": [
                "",
                "https://qqq.gtimg.cn/music/photo_new/T053XD000004YB3A10TqVg0.jpg",
                ""
            ]
        },
        {
            "name": "天涯",
            "qq": 36937883,
            "type": 3,
            "msg": [
                "",
                "https://qqq.gtimg.cn/music/photo_new/T053XD000002H3ZYU1caP5v.jpg",
                ""
            ]
        },
        {
            "name": "天涯",
            "qq": 36937883,
            "type": 3,
            "msg": [
                "",
                "https://qqq.gtimg.cn/music/photo_new/T053XD0000019RGDN3rEbDJ.jpg",
                ""
            ]
        },
        {
            "name": "天涯",
            "qq": 36937883,
            "type": 3,
            "msg": [
                "",
                "https://qqq.gtimg.cn/music/photo_new/T053XD000000pBm9x3FlLct.jpg",
                ""
            ]
        }
    ]
}